varclushi/__init__.py
varclushi/varclushi.py
varclushi-0.1.0.dist-info/METADATA
varclushi-0.1.0.dist-info/WHEEL
varclushi-0.1.0.dist-info/top_level.txt
varclushi-0.1.0.dist-info/RECORD
