Metadata-Version: 2.1
Name: varclushi
Version: 0.1.0
Summary: A package for variable clustering
Home-page: https://github.com/jingtt/varclushi
Author: Xuan Jing
Author-email: xuanjing@hotmail.com
License: UNKNOWN
Platform: UNKNOWN
Classifier: Intended Audience :: Science/Research
Classifier: Programming Language :: Python :: 3
Classifier: License :: OSI Approved :: GNU General Public License v3 (GPLv3)
Classifier: Operating System :: OS Independent
Classifier: Operating System :: Microsoft :: Windows
Classifier: Operating System :: POSIX :: Linux
Classifier: Operating System :: Unix
Requires-Dist: pandas
Requires-Dist: numpy
Requires-Dist: factor-analyzer (==0.3.1)
